gc_module_cua/__init__.py
gc_module_cua/capture_user_activity.py
gc_module_cua/functions.py
gc_module_cua/main.py
gc_module_cua/settings.py
gc_module_cua/tests/__init__.py
gc_module_cua/tests/capture_user_activity_test.py
gc_module_cua/tests/functions_test.py
gc_module_cua/tests/main_test.py
gc_module_cua/tests/settings_test.py
gc_module_cua/tests/sqlshell_test.py
gc_module_cua-1.43.dist-info/LICENSE
gc_module_cua-1.43.dist-info/METADATA
gc_module_cua-1.43.dist-info/WHEEL
gc_module_cua-1.43.dist-info/top_level.txt
gc_module_cua-1.43.dist-info/RECORD
